candump_utils/__init__.py
candump_utils/can_id.py
candump_utils/data_field_tc.py
candump_utils/data_field_tm.py
candump_utils/packet_header.py
candump_utils/py.typed
candump_utils/utils.py
lib_utils/__init__.py
lib_utils/addr_apid.py
lib_utils/config.py
lib_utils/endianness.py
lib_utils/exception.py
lib_utils/scos.py
lib_utils/warning.py
scripts/__init__.py
scripts/candump.py
yamcs_flatsat_utils/__init__.py
yamcs_flatsat_utils/_version.py
yamcs_flatsat_utils/command_processor.py
yamcs_flatsat_utils/mdb_utils.py
yamcs_flatsat_utils/py.typed
yamcs_flatsat_utils/yamcs_interface.py
endurance_flatsat_lib-0.0.6.dist-info/LICENSE
endurance_flatsat_lib-0.0.6.dist-info/METADATA
endurance_flatsat_lib-0.0.6.dist-info/WHEEL
endurance_flatsat_lib-0.0.6.dist-info/entry_points.txt
endurance_flatsat_lib-0.0.6.dist-info/top_level.txt
endurance_flatsat_lib-0.0.6.dist-info/RECORD
