Metadata-Version: 2.1
Name: endurance-flatsat-lib
Version: 0.0.6
Author-email: Romain Lhoussaine <romain@infiniteorbits.io>
License: MIT License
Project-URL: Source Code, https://github.com/infiniteorbits/endurance-flatsat-lib
Classifier: Development Status :: 4 - Beta
Classifier: License :: OSI Approved :: MIT License
Classifier: Intended Audience :: Developers
Classifier: Intended Audience :: Science/Research
Classifier: Operating System :: OS Independent
Classifier: Programming Language :: Python
Requires-Python: >=3.12
License-File: LICENSE
Requires-Dist: yamcs-client>=1.10.0
Requires-Dist: pandas>=2.2.3
Requires-Dist: pandas-stubs>=2.2.3.241009
Provides-Extra: dev
Requires-Dist: black; extra == "dev"
Requires-Dist: jupyter; extra == "dev"
Requires-Dist: mypy; extra == "dev"
Requires-Dist: pre-commit; extra == "dev"
Requires-Dist: pylint; extra == "dev"
Requires-Dist: pytest; extra == "dev"
Requires-Dist: pytest-cov; extra == "dev"
Requires-Dist: ruff; extra == "dev"
